odoo8_addon_base_delivery_carrier_files_document-8.0.1.0.2-py3.8-nspkg.pth
odoo_addons/base_delivery_carrier_files_document/README.rst
odoo_addons/base_delivery_carrier_files_document/__init__.py
odoo_addons/base_delivery_carrier_files_document/__openerp__.py
odoo_addons/base_delivery_carrier_files_document/demo/carrier_file_demo.xml
odoo_addons/base_delivery_carrier_files_document/i18n/base_delivery_carrier_files_document.pot
odoo_addons/base_delivery_carrier_files_document/i18n/de.po
odoo_addons/base_delivery_carrier_files_document/i18n/fr.po
odoo_addons/base_delivery_carrier_files_document/models/__init__.py
odoo_addons/base_delivery_carrier_files_document/models/delivery_carrier_file.py
odoo_addons/base_delivery_carrier_files_document/readme/CONTRIBUTORS.rst
odoo_addons/base_delivery_carrier_files_document/readme/DESCRIPTION.rst
odoo_addons/base_delivery_carrier_files_document/static/description/icon.png
odoo_addons/base_delivery_carrier_files_document/static/description/index.html
odoo_addons/base_delivery_carrier_files_document/tests/__init__.py
odoo_addons/base_delivery_carrier_files_document/tests/test_base_delivery_carrier_files_document.py
odoo_addons/base_delivery_carrier_files_document/views/carrier_file_view.xml
odoo8_addon_base_delivery_carrier_files_document-8.0.1.0.2.dist-info/METADATA
odoo8_addon_base_delivery_carrier_files_document-8.0.1.0.2.dist-info/WHEEL
odoo8_addon_base_delivery_carrier_files_document-8.0.1.0.2.dist-info/namespace_packages.txt
odoo8_addon_base_delivery_carrier_files_document-8.0.1.0.2.dist-info/top_level.txt
odoo8_addon_base_delivery_carrier_files_document-8.0.1.0.2.dist-info/RECORD
